README.md
setup.py
ugh/__init__.py
ugh.egg-info/PKG-INFO
ugh.egg-info/SOURCES.txt
ugh.egg-info/dependency_links.txt
ugh.egg-info/requires.txt
ugh.egg-info/top_level.txt