Metadata-Version: 1.2
Name: ugh
Version: 0.1.0
Summary: Use JSON templates to create terminal UI with urwid.
Home-page: https://github.com/meyer1994/ugh
Author: João Vicente Meyer
Author-email: UNKNOWN
License: GPL-3.0
Download-URL: https://github.com/meyer1994/ugh/archive/v0.1.0.tar.gz
Keywords: ugh urwid terminal curses development ui interface
Platform: UNKNOWN
Classifier: Development Status :: 4 - Beta
Classifier: Intended Audience :: Developers
Classifier: Topic :: Software Development :: Build Tools
Requires-Python: >=3.6
